{
  "boissons": [
    { "name": "Coca-Cola", "price": 3, "image": "/static/images/coca.jpg" },
    { "name": "Eau", "price": 2, "image": "/static/images/eau.jpg" },
    { "name": "Jus d'orange", "price": 4, "image": "/static/images/jus_orange.jpg" },
    { "name": "Ice Tea", "price": 3, "image": "/static/images/icetea.jpg" },
    { "name": "Café", "price": 2, "image": "/static/images/cafe.jpg" },
    { "name": "Shiven and the rock", "price": 16, "image": "/static/images/shiven.jpg" },
    { "name": "Le Slay original", "price": 20, "image": "/static/images/leslay.jpg" }
  ]
}